{"cameraMode":{"drawMode":0,"name":"Shaded","section":"Shading Mode"},"sceneLighting":true,"audioPlay":false,"sceneViewState":{"m_AlwaysRefresh":false,"showFog":true,"showSkybox":true,"showFlares":true,"showImageEffects":true,"showParticleSystems":true,"showVisualEffectGraphs":true,"m_FxEnabled":true},"in2DMode":false,"pivot":{"x":-0.2589932382106781,"y":5.388443470001221,"z":-2.4894704818725588},"rotation":{"x":-0.03330263867974281,"y":0.00659399526193738,"z":-0.00021991750691086054,"w":-0.9994270205497742},"size":7.33957576751709,"orthographic":false}